molecule_libvirt/__init__.py
molecule_libvirt/driver.py
molecule_libvirt/cookiecutter/scenario/driver/libvirt/cookiecutter.json
molecule_libvirt/cookiecutter/scenario/driver/libvirt/{{cookiecutter.molecule_directory}}/{{cookiecutter.scenario_name}}/INSTALL.rst
molecule_libvirt/cookiecutter/scenario/driver/libvirt/{{cookiecutter.molecule_directory}}/{{cookiecutter.scenario_name}}/converge.yml
molecule_libvirt/cookiecutter/scenario/driver/libvirt/{{cookiecutter.molecule_directory}}/{{cookiecutter.scenario_name}}/playbook.yml
molecule_libvirt/playbooks/create.yml
molecule_libvirt/playbooks/destroy.yml
molecule_libvirt/playbooks/templates/meta-data.j2
molecule_libvirt/playbooks/templates/user-data.j2
molecule_libvirt/playbooks/templates/network/network.xml.j2
molecule_libvirt/playbooks/templates/vm/vm.xml.j2
molecule_libvirt/test/__init__.py
molecule_libvirt/test/test_driver.py
molecule_libvirt/test/functional/.ansible-lint
molecule_libvirt/test/functional/__init__.py
molecule_libvirt/test/functional/conftest.py
molecule_libvirt/test/functional/test_libvirt.py
molecule_libvirt/test/scenarios/driver/libvirt/molecule/default/molecule.yml
molecule_libvirt/test/scenarios/driver/libvirt/molecule/default/playbook.yml
molecule_libvirt/test/scenarios/driver/libvirt/molecule/default/tests/test_default.py
molecule_libvirt/test/scenarios/driver/libvirt/molecule/multi-node/molecule.yml
molecule_libvirt/test/scenarios/driver/libvirt/molecule/multi-node/playbook.yml
molecule_libvirt/test/scenarios/driver/libvirt/molecule/multi-node/prepare.yml
molecule_libvirt/test/scenarios/driver/libvirt/molecule/multi-node/tests/__init__.py
molecule_libvirt/test/scenarios/driver/libvirt/molecule/multi-node/tests/test_default.py
molecule_libvirt-0.0.6.dist-info/LICENSE
molecule_libvirt-0.0.6.dist-info/METADATA
molecule_libvirt-0.0.6.dist-info/WHEEL
molecule_libvirt-0.0.6.dist-info/entry_points.txt
molecule_libvirt-0.0.6.dist-info/top_level.txt
molecule_libvirt-0.0.6.dist-info/RECORD
