Metadata-Version: 2.1
Name: molecule-libvirt
Version: 0.0.6
Summary: libvirt Molecule Plugin :: run molecule tests on libvirt
Home-page: https://github.com/ansible-community/molecule-libvirt
Author: Ansible by Red Hat
Author-email: info@ansible.com
Maintainer: Ansible by Red Hat
Maintainer-email: info@ansible.com
License: MIT
Project-URL: Bug Tracker, https://github.com/ansible-community/molecule-libvirt/issues
Project-URL: Release Management, https://github.com/ansible-community/molecule-libvirt/projects
Project-URL: CI: Zuul, https://dashboard.zuul.ansible.com/t/ansible/builds?project=ansible-community/molecule-libvirt
Project-URL: Discussions, https://github.com/ansible-community/molecule/discussions
Project-URL: Source Code, https://github.com/ansible-community/molecule-libvirt
Keywords: ansible,roles,testing,molecule,plugin,libvirt
Classifier: Development Status :: 2 - Pre-Alpha
Classifier: Environment :: Console
Classifier: Intended Audience :: Developers
Classifier: Intended Audience :: Information Technology
Classifier: Intended Audience :: System Administrators
Classifier: License :: OSI Approved :: MIT License
Classifier: Natural Language :: English
Classifier: Operating System :: OS Independent
Classifier: Programming Language :: Python :: 3
Classifier: Programming Language :: Python :: 3.6
Classifier: Programming Language :: Python :: 3.7
Classifier: Programming Language :: Python :: 3.8
Classifier: Programming Language :: Python :: 3.9
Classifier: Topic :: System :: Systems Administration
Classifier: Topic :: Utilities
Requires-Python: >=3.6
License-File: LICENSE
Requires-Dist: molecule (>=3.4.0)
Requires-Dist: pyyaml (>=5.1)
Requires-Dist: jmespath
Requires-Dist: lxml
Requires-Dist: netaddr
Provides-Extra: test
Requires-Dist: molecule[test] ; extra == 'test'
Requires-Dist: pytest-helpers-namespace ; extra == 'test'
